{
  "frame": {
    "board": [
      [
        -1,
        -1,
        -1,
        -1,
        -1,
        -1,
        -1,
        -1,
        -1,
        -1,
        -1,
        -1,
        -1,
        -1
      ],
      [
        -1,
        0,
        -1,
        0,
        0,
        0,
        0,
        0,
        0,
        0,
        0,
        0,
        0,
        -1
      ],
      [
        -1,
        0,
        -1,
        0,
        0,
        0,
        0,
        0,
        0,
        0,
        0,
        0,
        0,
        -1
      ],
      [
        -1,
        0,
        0,
        0,
        0,
        0,
        0,
        0,
        0,
        0,
        0,
        0,
        0,
        -1
      ],
      [
        -1,
        0,
        0,
        0,
        0,
        0,
        0,
        0,
        0,
        0,
        0,
        0,
        0,
        -1
      ],
      [
        -1,
        0,
        0,
        0,
        0,
        0,
        0,
        0,
        0,
        0,
        0,
        0,
        0,
        -1
      ],
      [
        -1,
        0,
        0,
        0,
        0,
        0,
        0,
        0,
        0,
        0,
        0,
        0,
        0,
        -1
      ],
      [
        -1,
        0,
        0,
        1,
        0,
        0,
        0,
        0,
        0,
        0,
        0,
        0,
        0,
        -1
      ],
      [
        -1,
        0,
        0,
        0,
        0,
        0,
        0,
        0,
        0,
        0,
        0,
        0,
        0,
        -1
      ],
      [
        -1,
        0,
        0,
        0,
        0,
        0,
        0,
        0,
        0,
        0,
        0,
        0,
        0,
        -1
      ],
      [
        -1,
        0,
        0,
        0,
        0,
        0,
        0,
        0,
        0,
        0,
        0,
        0,
        0,
        -1
      ],
      [
        -1,
        0,
        0,
        0,
        0,
        0,
        0,
        0,
        0,
        0,
        0,
        -1,
        0,
        -1
      ],
      [
        -1,
        0,
        0,
        0,
        0,
        0,
        0,
        0,
        0,
        0,
        0,
        -1,
        0,
        -1
      ],
      [
        -1,
        -1,
        -1,
        -1,
        -1,
        -1,
        -1,
        -1,
        -1,
        -1,
        -1,
        -1,
        -1,
        -1
      ]
    ],
    "food": {
      "x": 7,
      "y": 3
    },
    "height": 14,
    "kind": "multiplayer_snake",
    "snakes": {
      "snake_1": {
        "alive": true,
        "body": [
          {
            "x": 2,
            "y": 2
          },
          {
            "x": 1,
            "y": 2
          }
        ],
        "direction": "right",
        "food_eaten": 0,
        "invalid_moves": 0,
        "name": "Левый",
        "score": 0,
        "team_id": "left"
      },
      "snake_2": {
        "alive": true,
        "body": [
          {
            "x": 11,
            "y": 11
          },
          {
            "x": 12,
            "y": 11
          }
        ],
        "direction": "left",
        "food_eaten": 0,
        "invalid_moves": 0,
        "name": "Правый",
        "score": 0,
        "team_id": "right"
      }
    },
    "title": "Змейка мультиплеер",
    "width": 14
  },
  "phase": "running",
  "tick": 0
}
